{"cameraMode":{"drawMode":0,"name":"Shaded","section":"Shading Mode"},"sceneLighting":true,"audioPlay":false,"sceneViewState":{"showFog":true,"showMaterialUpdate":false,"showSkybox":true,"showFlares":true,"showImageEffects":true,"showParticleSystems":true},"in2DMode":false,"pivot":{"x":-28.676679611206056,"y":2.3318910598754885,"z":-0.41073182225227358},"rotation":{"x":-0.0032952853944152595,"y":-0.21031691133975984,"z":0.00042251215199939907,"w":-0.9778512716293335},"size":19.44987678527832,"orthographic":false}